msgpack_cxx/__init__.py
msgpack_cxx/include/__init__.py
msgpack_cxx/include/msgpack.hpp
msgpack_cxx/include/msgpack/assert.hpp
msgpack_cxx/include/msgpack/cpp_config.hpp
msgpack_cxx/include/msgpack/cpp_config_decl.hpp
msgpack_cxx/include/msgpack/cpp_version.hpp
msgpack_cxx/include/msgpack/create_object_visitor.hpp
msgpack_cxx/include/msgpack/create_object_visitor_decl.hpp
msgpack_cxx/include/msgpack/fbuffer.hpp
msgpack_cxx/include/msgpack/fbuffer_decl.hpp
msgpack_cxx/include/msgpack/gcc_atomic.hpp
msgpack_cxx/include/msgpack/iterator.hpp
msgpack_cxx/include/msgpack/iterator_decl.hpp
msgpack_cxx/include/msgpack/meta.hpp
msgpack_cxx/include/msgpack/meta_decl.hpp
msgpack_cxx/include/msgpack/nan_util.hpp~
msgpack_cxx/include/msgpack/null_visitor.hpp
msgpack_cxx/include/msgpack/null_visitor_decl.hpp
msgpack_cxx/include/msgpack/object.hpp
msgpack_cxx/include/msgpack/object_decl.hpp
msgpack_cxx/include/msgpack/object_fwd.hpp
msgpack_cxx/include/msgpack/object_fwd_decl.hpp
msgpack_cxx/include/msgpack/pack.hpp
msgpack_cxx/include/msgpack/pack_decl.hpp
msgpack_cxx/include/msgpack/parse.hpp
msgpack_cxx/include/msgpack/parse_decl.hpp
msgpack_cxx/include/msgpack/parse_return.hpp
msgpack_cxx/include/msgpack/predef.h
msgpack_cxx/include/msgpack/preprocessor.hpp
msgpack_cxx/include/msgpack/sbuffer.hpp
msgpack_cxx/include/msgpack/sbuffer_decl.hpp
msgpack_cxx/include/msgpack/sysdep.hpp
msgpack_cxx/include/msgpack/type.hpp
msgpack_cxx/include/msgpack/unpack.hpp
msgpack_cxx/include/msgpack/unpack_decl.hpp
msgpack_cxx/include/msgpack/unpack_define.hpp
msgpack_cxx/include/msgpack/unpack_exception.hpp
msgpack_cxx/include/msgpack/version.hpp
msgpack_cxx/include/msgpack/version_master.hpp
msgpack_cxx/include/msgpack/versioning.hpp
msgpack_cxx/include/msgpack/vrefbuffer.hpp
msgpack_cxx/include/msgpack/vrefbuffer_decl.hpp
msgpack_cxx/include/msgpack/x3_parse.hpp
msgpack_cxx/include/msgpack/x3_parse_decl.hpp
msgpack_cxx/include/msgpack/x3_unpack.hpp
msgpack_cxx-7.0.0.dist-info/LICENSE
msgpack_cxx-7.0.0.dist-info/METADATA
msgpack_cxx-7.0.0.dist-info/WHEEL
msgpack_cxx-7.0.0.dist-info/top_level.txt
msgpack_cxx-7.0.0.dist-info/RECORD
