Metadata-Version: 2.1
Name: msgpack-cxx
Version: 7.0.0
Summary: Repackaging of msgpack-cxx distributed via PyPI
Author-email: Alliander Dynamic Grid Calculation <dynamic.grid.calculation@alliander.com>
License: BSL-1.0
Project-URL: Home-page, https://msgpack.org/
Project-URL: GitHub, https://github.com/msgpack/msgpack-c/tree/cpp_master
Project-URL: Documentation, https://github.com/msgpack/msgpack-c/tree/cpp_master
Classifier: Programming Language :: C++
Classifier: Development Status :: 5 - Production/Stable
Classifier: Intended Audience :: Developers
Classifier: License :: OSI Approved :: Boost Software License 1.0 (BSL-1.0)
Classifier: Operating System :: Microsoft :: Windows
Classifier: Operating System :: POSIX :: Linux
Classifier: Operating System :: MacOS
Classifier: Topic :: File Formats
Classifier: Topic :: Software Development :: Libraries
License-File: LICENSE
Requires-Dist: importlib-resources
Provides-Extra: dev
Requires-Dist: pytest; extra == "dev"
